yasiu_math/__init__.py
yasiu_math/convolve.py
yasiu_math/math.py
yasiu_math-0.1.2.dist-info/LICENSE
yasiu_math-0.1.2.dist-info/METADATA
yasiu_math-0.1.2.dist-info/WHEEL
yasiu_math-0.1.2.dist-info/top_level.txt
yasiu_math-0.1.2.dist-info/RECORD
